libpkgs/__init__.py
libpkgs/libpkgs.py
libpkgs-0.0.3.dist-info/METADATA
libpkgs-0.0.3.dist-info/WHEEL
libpkgs-0.0.3.dist-info/top_level.txt
libpkgs-0.0.3.dist-info/RECORD
