Metadata-Version: 2.1
Name: libpkgs
Version: 0.0.3
Summary: An open-source python package to find all the packages with their versions used inside an ipynb notebook
Home-page: https://github.com/U77w41/
Author: Ujjwal Chowdhury
Author-email: <u77w41@gmail.com>
License: MIT
Keywords: python,ipynb,packages
